addresses/__init__.py
addresses/address.json
artifacts/AccessList.json
artifacts/AccessListFactory.json
artifacts/Address.json
artifacts/BConst.json
artifacts/BFactory.json
artifacts/BMath.json
artifacts/BNum.json
artifacts/BPool.json
artifacts/BToken.json
artifacts/BTokenBase.json
artifacts/BatchPayments.json
artifacts/Booster.json
artifacts/Context.json
artifacts/DFRewards.json
artifacts/DFStrategyV1.json
artifacts/Deployer.json
artifacts/Dispenser.json
artifacts/Distribute.json
artifacts/ERC165.json
artifacts/ERC20Roles.json
artifacts/ERC20Template.json
artifacts/ERC20Template3.json
artifacts/ERC20Template4.json
artifacts/ERC20TemplateEnterprise.json
artifacts/ERC721.json
artifacts/ERC721Factory.json
artifacts/ERC721RolesAddress.json
artifacts/ERC721Template.json
artifacts/ERC725Ocean.json
artifacts/EnterpriseFeeCollector.json
artifacts/EnumerableMap.json
artifacts/EnumerableSet.json
artifacts/Escrow.json
artifacts/FactoryRouter.json
artifacts/FixedRateExchange.json
artifacts/FixedRateExchangeEnterprise.json
artifacts/IAccessList.json
artifacts/IAccessListContract.json
artifacts/IAccessListFactory.json
artifacts/IDFRewards.json
artifacts/IDispenser.json
artifacts/IERC165.json
artifacts/IERC20.json
artifacts/IERC20Template.json
artifacts/IERC20Template3.json
artifacts/IERC721.json
artifacts/IERC721Enumerable.json
artifacts/IERC721Metadata.json
artifacts/IERC721Receiver.json
artifacts/IERC721Template.json
artifacts/IERC725X.json
artifacts/IERC725Y.json
artifacts/IEnterpriseFeeCollector.json
artifacts/IFactory.json
artifacts/IFactoryRouter.json
artifacts/IFixedRateExchange.json
artifacts/IPool.json
artifacts/ISideStaking.json
artifacts/ISplitter.json
artifacts/IVestingContract.json
artifacts/IveFeeDistributor.json
artifacts/IveOCEAN.json
artifacts/MockERC20.json
artifacts/MockERC20Decimals.json
artifacts/MockExchange.json
artifacts/MockOcean.json
artifacts/MockOldDT.json
artifacts/OPFCommunityFeeCollector.json
artifacts/OceanToken.json
artifacts/Ownable.json
ocean_contracts-2.4.1.dist-info/METADATA
ocean_contracts-2.4.1.dist-info/WHEEL
ocean_contracts-2.4.1.dist-info/top_level.txt
ocean_contracts-2.4.1.dist-info/RECORD
