Metadata-Version: 2.4
Name: ocean-contracts
Version: 2.4.1
Summary: 🐳 Ocean Protocol L1 - v4
Home-page: https://github.com/oceanprotocol/contracts
Author: leucothia
Author-email: devops@oceanprotocol.com
Project-URL: Bug Tracker, https://github.com/oceanprotocol/contracts/issues
Keywords: ocean-contracts
Classifier: Development Status :: 3 - Alpha
Classifier: Intended Audience :: Developers
Classifier: License :: OSI Approved :: Apache Software License
Classifier: Natural Language :: English
Classifier: Programming Language :: Python :: 3.6
Requires-Python: >=3.6
